imagededup_cli/__init__.py
imagededup_cli/imagededup_cli.py
imagededup_cli-1.0.4.dist-info/LICENSE
imagededup_cli-1.0.4.dist-info/METADATA
imagededup_cli-1.0.4.dist-info/WHEEL
imagededup_cli-1.0.4.dist-info/entry_points.txt
imagededup_cli-1.0.4.dist-info/top_level.txt
imagededup_cli-1.0.4.dist-info/RECORD
