Metadata-Version: 2.1
Name: imagededup-cli
Version: 1.0.4
Summary: A tool to remove duplicate jpg images
Home-page: https://github.com/tadeasf/imagededup-cli
Author: Tadeas Fort
Author-email: taddy.fort@gmail.com
Classifier: Programming Language :: Python :: 3
Classifier: License :: OSI Approved :: MIT License
Classifier: Operating System :: OS Independent
Requires-Python: >=3.9
License-File: LICENSE
Requires-Dist: rich-click
Requires-Dist: tk
Requires-Dist: tqdm
Requires-Dist: loguru
Requires-Dist: imagededup
